README.txt
setup.cfg
setup.py
ComplexSystems.egg-info/PKG-INFO
ComplexSystems.egg-info/SOURCES.txt
ComplexSystems.egg-info/dependency_links.txt
ComplexSystems.egg-info/requires.txt
ComplexSystems.egg-info/top_level.txt
complex_systems/__init__.py
complex_systems/diffusion.py
complex_systems/dygraph.py
complex_systems/pgg.py
complex_systems/pgg_diffusion.py
complex_systems/quasi_unit_disk_graph.py
complex_systems/mobility/__init__.py
complex_systems/mobility/distance.py
complex_systems/mobility/levy_walk.py
complex_systems/mobility/stabrnd.py
complex_systems/spatial/__init__.py
complex_systems/spatial/kernel_density_geo.py