Metadata-Version: 1.1
Name: ComplexSystems
Version: 0.3.0.27
Summary: Toolbox for Complex Sytems including : Public Good Game, Human Based Mobility Models
Home-page: http://bitbucket.org/vgauthier/complex-systems/
Author: Vincent Gauthier
Author-email: vgauthier@luxbulb.org
License: MIT
Keywords: complex systems,Levy flight,human mobility
Platform: any
Classifier: License :: OSI Approved :: MIT License
Classifier: Programming Language :: Python
Classifier: Programming Language :: Python :: 2.7
Classifier: Operating System :: OS Independent
Classifier: Topic :: Scientific/Engineering :: Mathematics
Classifier: Development Status :: 4 - Beta
Classifier: Intended Audience :: Science/Research
Requires: numpy
Requires: pylab
